win_gpg_agent/__init__.py
win_gpg_agent/cli.py
win_gpg_agent/config.py
win_gpg_agent/gpg_agent.py
win_gpg_agent/ssh_agent.py
win_gpg_agent/util.py
win_gpg_agent/windows_component.py
win_gpg_agent-0.1.2.dist-info/entry_points.txt
win_gpg_agent-0.1.2.dist-info/WHEEL
win_gpg_agent-0.1.2.dist-info/METADATA
win_gpg_agent-0.1.2.dist-info/RECORD
