Metadata-Version: 2.1
Name: win-gpg-agent
Version: 0.1.2
Summary: Utility for tunnelling gpg-agent and ssh-agent from Windows to WSL.
Home-page: https://github.com/chvolkmann/win_gpg_agent
License: MIT
Keywords: win-gpg-agent,gpg-agent,ssh-agent,gpg,wsl
Author: Christian Volkmann
Author-email: ch.volkmann@gmail.com
Requires-Python: >=3.7,<4.0
Classifier: License :: OSI Approved :: MIT License
Classifier: Programming Language :: Python :: 3
Classifier: Programming Language :: Python :: 3.7
Classifier: Programming Language :: Python :: 3.8
Classifier: Programming Language :: Python :: 3.9
Requires-Dist: click (>=8.0.3,<9.0.0)
Requires-Dist: psutil (>=5.9.0,<6.0.0)
Project-URL: Repository, https://github.com/chvolkmann/win_gpg_agent
